papermill_mlflow_handler/__init__.py
papermill_mlflow_handler-1.0.1.dist-info/LICENSE.txt
papermill_mlflow_handler-1.0.1.dist-info/METADATA
papermill_mlflow_handler-1.0.1.dist-info/WHEEL
papermill_mlflow_handler-1.0.1.dist-info/entry_points.txt
papermill_mlflow_handler-1.0.1.dist-info/top_level.txt
papermill_mlflow_handler-1.0.1.dist-info/RECORD
