Metadata-Version: 2.1
Name: papermill-mlflow-handler
Version: 1.0.1
Summary: MLFlow handler for papermill.
Home-page: UNKNOWN
License: ['MIT']
Platform: UNKNOWN
Requires-Python: >=3.6
Requires-Dist: papermill
Requires-Dist: mlflow
Requires-Dist: google-cloud-storage
